pyclf/__init__.py
pyclf/lda/__init__.py
pyclf/lda/benchmark/__init__.py
pyclf/lda/classification/__init__.py
pyclf/lda/classification/covariance.py
pyclf/lda/classification/toeplitzlda.py
pyclf/lda/classification/unsupervised.py
pyclf/lda/usup_replay/__init__.py
pyclf/lda/usup_replay/llp.py
pyclf/lda/usup_replay/visual_speller.py
pyclf_bci-0.0.5.dist-info/LICENSE
pyclf_bci-0.0.5.dist-info/METADATA
pyclf_bci-0.0.5.dist-info/WHEEL
pyclf_bci-0.0.5.dist-info/top_level.txt
pyclf_bci-0.0.5.dist-info/RECORD
