Metadata-Version: 2.1
Name: pyclf-bci
Version: 0.0.5
Summary: An implementation of various classifier for bci application.
Home-page: https://github.com/simonkojima/pyclf
Author: Simon Kojima
Author-email: simon.kojima@outlook.com
Project-URL: Bug Tracker, https://github.com/simonkojima/pyclf/issues
Classifier: Programming Language :: Python :: 3
Classifier: License :: OSI Approved :: MIT License
Classifier: Operating System :: OS Independent
Requires-Python: >=3.6
License-File: LICENSE
Requires-Dist: numpy
Requires-Dist: sklearn
Requires-Dist: blockmatrix
